MANIFEST.in
setup.cfg
setup.py
ampcrowd_client/__init__.py
ampcrowd_client/client.py
ampcrowd_client/conn.py
ampcrowd_client/response_server.py
ampcrowd_client.egg-info/PKG-INFO
ampcrowd_client.egg-info/SOURCES.txt
ampcrowd_client.egg-info/dependency_links.txt
ampcrowd_client.egg-info/requires.txt
ampcrowd_client.egg-info/top_level.txt