Metadata-Version: 1.0
Name: ampcrowd-client
Version: 0.0.4
Summary: A python client for using the AMPCrowd service.
Home-page: http://github.com/amplab/ampcrowd-client-py
Author: Daniel Haas
Author-email: dhaas@cs.berkeley.edu
License: Apache License 2.0
Platform: UNKNOWN
